{"version": 0.6, "generator": "Overpass API 0.7.62.7 375dc00a", "osm3s": {"timestamp_osm_base": "2025-08-05T14:05:41Z", "copyright": "The data included in this document is from www.openstreetmap.org. The data is made available under ODbL."}, "elements": [{"type": "node", "id": 165738452, "lat": 52.5931629, "lon": 13.4499026}, {"type": "node", "id": 165738453, "lat": 52.5926118, "lon": 13.4473778}, {"type": "node", "id": 165738454, "lat": 52.5920766, "lon": 13.4459251}, {"type": "node", "id": 311482767, "lat": 52.5933588, "lon": 13.4487631}, {"type": "node", "id": 311482838, "lat": 52.5926426, "lon": 13.4468734, "tags": {"access": "yes", "leisure": "playground", "wheelchair": "no"}}, {"type": "node", "id": 434481239, "lat": 52.5930118, "lon": 13.4570289, "tags": {"addr:city": "Berlin", "addr:housenumber": "44", "addr:postcode": "13129", "addr:street": "Alt-Blankenburg", "amenity": "cafe", "name": "Kaffeehaus Blankenburg", "opening_hours": "Mo-Su 10:00-19:00", "outdoor_seating": "yes", "phone": "+494074398648", "website": "http://www.kaffeehausblankenburg.de/", "wheelchair": "yes"}}, {"type": "node", "id": 435296511, "lat": 52.5969623, "lon": 13.4647052}, {"type": "node", "id": 435296514, "lat": 52.5968875, "lon": 13.4650483}, {"type": "node", "id": 435296516, "lat": 52.5972902, "lon": 13.4652864}, {"type": "node", "id": 435296519, "lat": 52.5973649, "lon": 13.4649437}, {"type": "node", "id": 503335098, "lat": 52.5782253, "lon": 13.4610488}, {"type": "node", "id": 503335099, "lat": 52.5786212, "lon": 13.4614349}, {"type": "node", "id": 503335100, "lat": 52.5784944, "lon": 13.4617868}, {"type": "node", "id": 503335101, "lat": 52.5780985, "lon": 13.4614008}, {"type": "node", "id": 559696898, "lat": 52.5771588, "lon": 13.4536873}, {"type": "node", "id": 899455795, "lat": 52.5930714, "lon": 13.4475437}, {"type": "node", "id": 899501425, "lat": 52.5941084, "lon": 13.4485893}, {"type": "node", "id": 899501431, "lat": 52.593185, "lon": 13.447442}, {"type": "node", "id": 899501468, "lat": 52.5930005, "lon": 13.4475775}, {"type": "node", "id": 899501478, "lat": 52.592915, "lon": 13.4488771}, {"type": "node", "id": 899501485, "lat": 52.5942844, "lon": 13.4496076}, {"type": "node", "id": 899501869, "lat": 52.5928199, "lon": 13.4473112}, {"type": "node", "id": 899501895, "lat": 52.5933607, "lon": 13.4468098}, {"type": "node", "id": 901013001, "lat": 52.5909543, "lon": 13.4453656, "tags": {"brand": "Netto Marken-Discount", "brand:wikidata": "Q879858", "brand:wikipedia": "de:Netto Marken-Discount", "check_date:opening_hours": "2025-02-06", "name": "Netto Marken-Discount", "opening_hours": "Mo-Sa 07:00-21:00", "shop": "supermarket", "website": "https://www.netto-online.de/filialen/Berlin-Blankenburg/Bahnhofstrasse-31-a/5115/", "wheelchair": "yes"}}, {"type": "node", "id": 912063508, "lat": 52.5905571, "lon": 13.4438115}, {"type": "node", "id": 912063514, "lat": 52.5919391, "lon": 13.4453568}, {"type": "node", "id": 1636871893, "lat": 52.5916047, "lon": 13.4499688}, {"type": "node", "id": 1828398435, "lat": 52.5739139, "lon": 13.4496924}, {"type": "node", "id": 1828398584, "lat": 52.5739129, "lon": 13.4494343}, {"type": "node", "id": 2414356025, "lat": 52.5970259, "lon": 13.4647428}, {"type": "node", "id": 2414356026, "lat": 52.5970421, "lon": 13.4646682}, {"type": "node", "id": 2414356030, "lat": 52.5970889, "lon": 13.4646959}, {"type": "node", "id": 2630495284, "lat": 52.5944792, "lon": 13.4616496}, {"type": "node", "id": 2630495288, "lat": 52.5947134, "lon": 13.4627039}, {"type": "node", "id": 2630495295, "lat": 52.5960349, "lon": 13.4625958}, {"type": "node", "id": 2637105496, "lat": 52.592688, "lon": 13.4546877}, {"type": "node", "id": 2637167639, "lat": 52.5932539, "lon": 13.4489242, "tags": {"access": "yes", "leisure": "playground"}}, {"type": "node", "id": 2637167640, "lat": 52.5935114, "lon": 13.4493091, "tags": {"access": "yes", "leisure": "playground"}}, {"type": "node", "id": 2637167738, "lat": 52.5930853, "lon": 13.4579767, "tags": {"amenity": "doctors", "check_date:opening_hours": "2023-08-14", "healthcare": "doctor", "healthcare:speciality": "general", "name": "\u00c4rtzin f\u00fcr Allgemeinmedizin Dr. med Wladow", "opening_hours": "Mo 15:00-19:00; Tu 08:00-13:00; We 08:00-10:00; Th 08:00-13:00; Fr 14:00-18:00", "wheelchair": "no"}}, {"type": "node", "id": 2637167803, "lat": 52.5974843, "lon": 13.4661069}, {"type": "node", "id": 2637167804, "lat": 52.5977517, "lon": 13.4662011}, {"type": "node", "id": 2637167805, "lat": 52.597761, "lon": 13.4661297}, {"type": "node", "id": 2637167806, "lat": 52.5978187, "lon": 13.46615}, {"type": "node", "id": 2637167807, "lat": 52.5978099, "lon": 13.4662179}, {"type": "node", "id": 2637167808, "lat": 52.5978395, "lon": 13.4662283}, {"type": "node", "id": 2780155896, "lat": 52.590936, "lon": 13.4427298, "tags": {"addr:city": "Berlin", "amenity": "restaurant", "cuisine": "kebab", "indoor_seating": "yes", "name": "Prime Kebab", "outdoor_seating": "yes", "takeaway": "yes", "wheelchair": "limited"}}, {"type": "node", "id": 2930932221, "lat": 52.5926029, "lon": 13.4549314}, {"type": "node", "id": 2930936306, "lat": 52.5970726, "lon": 13.4647709}, {"type": "node", "id": 2930937203, "lat": 52.5934018, "lon": 13.4552707, "tags": {"addr:city": "Berlin", "addr:country": "DE", "addr:housenumber": "29", "addr:postcode": "13129", "addr:street": "Alt-Blankenburg", "addr:suburb": "Blankenburg", "amenity": "doctors", "healthcare": "doctor", "healthcare:speciality": "ophthalmology", "name": "Augenarzt", "source": "Geoportal Berlin / Hauskoordinaten", "wheelchair": "limited"}}, {"type": "node", "id": 2930937809, "lat": 52.5974296, "lon": 13.4665281}, {"type": "node", "id": 2930965442, "lat": 52.5956118, "lon": 13.4631802}, {"type": "node", "id": 2932236142, "lat": 52.5918613, "lon": 13.4538269}, {"type": "node", "id": 2932236612, "lat": 52.5915693, "lon": 13.4541501}, {"type": "node", "id": 2932237021, "lat": 52.5915668, "lon": 13.4538855}, {"type": "node", "id": 2932237157, "lat": 52.5918613, "lon": 13.454142}, {"type": "node", "id": 2932237979, "lat": 52.5926019, "lon": 13.4549195}, {"type": "node", "id": 2932238411, "lat": 52.5925857, "lon": 13.4547094}, {"type": "node", "id": 2932238511, "lat": 52.5927039, "lon": 13.4549109}, {"type": "node", "id": 2932362602, "lat": 52.5939096, "lon": 13.4612665}, {"type": "node", "id": 2932362608, "lat": 52.5940368, "lon": 13.4616306}, {"type": "node", "id": 2932362610, "lat": 52.5940636, "lon": 13.4617747}, {"type": "node", "id": 2932362622, "lat": 52.5942177, "lon": 13.4609141}, {"type": "node", "id": 2932362712, "lat": 52.5941218, "lon": 13.460859}, {"type": "node", "id": 2932362802, "lat": 52.5937621, "lon": 13.4609791}, {"type": "node", "id": 2932363001, "lat": 52.5937991, "lon": 13.4610987}, {"type": "node", "id": 2932363019, "lat": 52.5943425, "lon": 13.4612921}, {"type": "node", "id": 2932363036, "lat": 52.5957893, "lon": 13.4644484}, {"type": "node", "id": 2932363202, "lat": 52.5944705, "lon": 13.4619459}, {"type": "node", "id": 4365384392, "lat": 52.5937649, "lon": 13.4607566, "tags": {"addr:city": "Berlin", "addr:housenumber": "67a", "addr:postcode": "13129", "addr:street": "Alt-Blankenburg", "amenity": "pharmacy", "healthcare": "pharmacy", "name": "L\u00f6wenburg-Apotheke", "opening_hours": "Mo-Fr 08:00-19:30; Sa 08:30-14:00; Su,PH off", "phone": "+493094516340", "website": "https://www.loewenburg-apotheke.de/", "wheelchair": "yes"}}, {"type": "node", "id": 4519611136, "lat": 52.5919704, "lon": 13.4457976}, {"type": "node", "id": 4519611137, "lat": 52.5918438, "lon": 13.4454655}, {"type": "node", "id": 4554145625, "lat": 52.5916669, "lon": 13.4504498}, {"type": "node", "id": 4554145633, "lat": 52.5914658, "lon": 13.4500482}, {"type": "node", "id": 4554145634, "lat": 52.5914801, "lon": 13.4501838}, {"type": "node", "id": 4554145635, "lat": 52.5914926, "lon": 13.450185}, {"type": "node", "id": 4554145636, "lat": 52.5915338, "lon": 13.4502122}, {"type": "node", "id": 4554145637, "lat": 52.5915606, "lon": 13.4502713}, {"type": "node", "id": 4554145638, "lat": 52.5916432, "lon": 13.4502475}, {"type": "node", "id": 4587281834, "lat": 52.5901223, "lon": 13.4539018}, {"type": "node", "id": 4587281836, "lat": 52.5900868, "lon": 13.454085}, {"type": "node", "id": 4587281843, "lat": 52.5899337, "lon": 13.4540564}, {"type": "node", "id": 4587281844, "lat": 52.5901006, "lon": 13.4540597}, {"type": "node", "id": 4587281845, "lat": 52.5900669, "lon": 13.4538249}, {"type": "node", "id": 4587281846, "lat": 52.5899513, "lon": 13.4538022}, {"type": "node", "id": 4630533834, "lat": 52.5946248, "lon": 13.4635104}, {"type": "node", "id": 4630533836, "lat": 52.5959092, "lon": 13.4632306}, {"type": "node", "id": 4899844400, "lat": 52.5915492, "lon": 13.4502373}, {"type": "node", "id": 4899844401, "lat": 52.591514, "lon": 13.4501935}, {"type": "node", "id": 4937114677, "lat": 52.5789553, "lon": 13.4500358}, {"type": "node", "id": 5764073129, "lat": 52.591774, "lon": 13.4499382}, {"type": "node", "id": 5764073130, "lat": 52.5917359, "lon": 13.4499491}, {"type": "node", "id": 5764073131, "lat": 52.5917341, "lon": 13.4499318}, {"type": "node", "id": 5764073132, "lat": 52.5917722, "lon": 13.4499216}, {"type": "node", "id": 5764073139, "lat": 52.5920853, "lon": 13.449832}, {"type": "node", "id": 5764073140, "lat": 52.5920969, "lon": 13.4499373, "tags": {"barrier": "gate"}}, {"type": "node", "id": 5764073141, "lat": 52.591456, "lon": 13.4499389}, {"type": "node", "id": 5764073142, "lat": 52.5915968, "lon": 13.4498939}, {"type": "node", "id": 5764073143, "lat": 52.5916817, "lon": 13.4505875}, {"type": "node", "id": 5764073144, "lat": 52.5923118, "lon": 13.4504083}, {"type": "node", "id": 5764073145, "lat": 52.5922903, "lon": 13.4502206}, {"type": "node", "id": 5764073146, "lat": 52.5921338, "lon": 13.4502681}, {"type": "node", "id": 5764073147, "lat": 52.592087, "lon": 13.4498488}, {"type": "node", "id": 5764146057, "lat": 52.5963778, "lon": 13.4639558}, {"type": "node", "id": 5764146081, "lat": 52.5958368, "lon": 13.4642013}, {"type": "node", "id": 5764146083, "lat": 52.596223, "lon": 13.4646935}, {"type": "node", "id": 5764146091, "lat": 52.5975305, "lon": 13.4642073}, {"type": "node", "id": 5764146092, "lat": 52.5975687, "lon": 13.4639194}, {"type": "node", "id": 5764146105, "lat": 52.5972959, "lon": 13.4632681}, {"type": "node", "id": 6467023816, "lat": 52.5937254, "lon": 13.4603373, "tags": {"amenity": "doctors", "healthcare": "doctor", "healthcare:speciality": "general;internal", "name": "Dr. med. Mirjam Schumann", "website": "https://www.arztpraxis-mirjam-schumann.de/"}}, {"type": "node", "id": 7792241322, "lat": 52.5976548, "lon": 13.463457}, {"type": "node", "id": 7792343683, "lat": 52.5941996, "lon": 13.4489149}, {"type": "node", "id": 9433267906, "lat": 52.5769871, "lon": 13.4533874}, {"type": "node", "id": 9433295333, "lat": 52.5774368, "lon": 13.4512371}, {"type": "node", "id": 9433295346, "lat": 52.5743541, "lon": 13.4497735}, {"type": "node", "id": 9433295347, "lat": 52.5739846, "lon": 13.4494175}, {"type": "node", "id": 9433295348, "lat": 52.5739932, "lon": 13.4491496}, {"type": "node", "id": 9433295349, "lat": 52.5744687, "lon": 13.4491795}, {"type": "node", "id": 9433295350, "lat": 52.5745983, "lon": 13.4492694}, {"type": "node", "id": 9433295351, "lat": 52.5749132, "lon": 13.4496184}, {"type": "node", "id": 9433295352, "lat": 52.5748254, "lon": 13.4498246}, {"type": "node", "id": 9433295353, "lat": 52.5750267, "lon": 13.45017}, {"type": "node", "id": 9433295354, "lat": 52.5752142, "lon": 13.4504009}, {"type": "node", "id": 9433295355, "lat": 52.5754326, "lon": 13.4505436}, {"type": "node", "id": 9433295356, "lat": 52.5756458, "lon": 13.4507745}, {"type": "node", "id": 9433295357, "lat": 52.575905, "lon": 13.4511481}, {"type": "node", "id": 9433295358, "lat": 52.5761384, "lon": 13.4514354}, {"type": "node", "id": 9433295359, "lat": 52.5763591, "lon": 13.4515852}, {"type": "node", "id": 9433295360, "lat": 52.576509, "lon": 13.4516416}, {"type": "node", "id": 9433295361, "lat": 52.5766172, "lon": 13.4516398}, {"type": "node", "id": 9433295362, "lat": 52.5767714, "lon": 13.451601}, {"type": "node", "id": 9433295363, "lat": 52.5769867, "lon": 13.4515341}, {"type": "node", "id": 9433295364, "lat": 52.577188, "lon": 13.4514301}, {"type": "node", "id": 9433295365, "lat": 52.5772619, "lon": 13.4513702}, {"type": "node", "id": 9433295366, "lat": 52.5773433, "lon": 13.4513085}, {"type": "node", "id": 9433295367, "lat": 52.5774472, "lon": 13.4512292}, {"type": "node", "id": 9433295368, "lat": 52.5775618, "lon": 13.4510406}, {"type": "node", "id": 9433295369, "lat": 52.5777813, "lon": 13.4508379}, {"type": "node", "id": 9433295370, "lat": 52.5779291, "lon": 13.45057}, {"type": "node", "id": 9433295371, "lat": 52.578078, "lon": 13.4503639}, {"type": "node", "id": 9433295372, "lat": 52.5784432, "lon": 13.4498563}, {"type": "node", "id": 9433295373, "lat": 52.5785968, "lon": 13.4496355}, {"type": "node", "id": 9433295374, "lat": 52.5779901, "lon": 13.4511816}, {"type": "node", "id": 9433295375, "lat": 52.5757411, "lon": 13.4512115}, {"type": "node", "id": 9433295377, "lat": 52.5738839, "lon": 13.4494457}, {"type": "node", "id": 9701267496, "lat": 52.5906625, "lon": 13.444797}, {"type": "node", "id": 9701267497, "lat": 52.5905662, "lon": 13.4439648}, {"type": "node", "id": 10539271403, "lat": 52.593667, "lon": 13.4537178, "tags": {"leisure": "playground"}}, {"type": "node", "id": 10619988384, "lat": 52.5912512, "lon": 13.4448155}, {"type": "node", "id": 10619988387, "lat": 52.5911068, "lon": 13.4446572}, {"type": "node", "id": 11982696956, "lat": 52.5977915, "lon": 13.4665984}, {"type": "node", "id": 11982696957, "lat": 52.5975675, "lon": 13.4665196}, {"type": "node", "id": 11982696958, "lat": 52.5975604, "lon": 13.4665742}, {"type": "node", "id": 12039816186, "lat": 52.5973377, "lon": 13.4641609}, {"type": "way", "id": 37340843, "nodes": [435296511, 435296514, 435296516, 435296519, 2930936306, 2414356030, 2414356026, 2414356025, 435296511], "tags": {"addr:city": "Berlin", "addr:country": "DE", "addr:housenumber": "26", "addr:postcode": "13129", "addr:street": "Treseburger Stra\u00dfe", "addr:suburb": "Blankenburg", "brand": "Aldi Nord", "brand:wikidata": "Q41171373", "brand:wikipedia": "en:Aldi", "building": "retail", "building:levels": "1", "building:use": "retail", "check_date:opening_hours": "2023-09-18", "name": "Aldi", "opening_hours": "Mo-Sa 07:00-21:00", "roof:shape": "gabled", "shop": "supermarket", "source": "Geoportal Berlin / Hauskoordinaten", "wheelchair": "yes"}}, {"type": "way", "id": 41198493, "nodes": [503335098, 503335099, 503335100, 503335101, 503335098], "tags": {"access": "yes", "leisure": "playground", "surface": "dirt"}}, {"type": "way", "id": 77491365, "nodes": [912063508, 9701267497, 9701267496, 10619988387, 10619988384, 4519611137, 4519611136, 165738454, 165738453, 899501869, 899501468, 899455795, 899501431, 899501895, 912063514, 912063508], "tags": {"leisure": "park", "protection_title": "Gesch\u00fctzte Gr\u00fcnanlage"}}, {"type": "way", "id": 258342170, "nodes": [2637105496, 2932238411, 2932237979, 2930932221, 2932238511, 2637105496], "tags": {"addr:city": "Berlin", "addr:country": "DE", "addr:housenumber": "24", "addr:postcode": "13129", "addr:street": "Alt-Blankenburg", "addr:suburb": "Blankenburg", "amenity": "restaurant", "building": "yes", "capacity": "200", "contact:phone": "+49 30 47485977", "cuisine": "greek", "description": "Telefon f\u00fcr Bestellungen bei Selbstabholung: 030-47 485 977", "name": "Syrtaki", "opening_hours": "Mo-Su 12:00-23:00", "payment:credit_cards": "no", "payment:girocard": "yes", "phone": "+49 30 47485977", "source": "Geoportal Berlin / Hauskoordinaten", "takeaway": "yes", "website": "https://syrtaki-blankenburg.com/", "wheelchair": "limited"}}, {"type": "way", "id": 258350531, "nodes": [11982696956, 11982696957, 11982696958, 2930937809, 2637167803, 2637167804, 2637167805, 2637167806, 2637167807, 2637167808, 11982696956], "tags": {"addr:city": "Berlin", "addr:country": "DE", "addr:housenumber": "29", "addr:postcode": "13129", "addr:street": "Treseburger Stra\u00dfe", "addr:suburb": "Blankenburg", "brand": "Netto Marken-Discount", "brand:wikidata": "Q879858", "brand:wikipedia": "de:Netto Marken-Discount", "building": "retail", "building:levels": "1", "check_date:opening_hours": "2023-09-18", "name": "Netto Marken-Discount", "opening_hours": "Mo-Sa 07:00-21:00; PH,Su off", "shop": "supermarket", "source": "Geoportal Berlin / Hauskoordinaten", "website": "https://www.netto-online.de/filialen/Berlin-Pankow/Treseburger-Str-29/7464/", "wheelchair": "yes"}}, {"type": "way", "id": 289674751, "nodes": [2932236142, 2932237157, 2932236612, 2932237021, 2932236142], "tags": {"leisure": "playground"}}, {"type": "way", "id": 374835498, "nodes": [899501478, 165738452, 899501485, 7792343683, 899501425, 311482767, 899501478], "tags": {"leisure": "park", "protection_title": "Gesch\u00fctzte Gr\u00fcnanlage"}}, {"type": "way", "id": 463469290, "nodes": [4587281846, 4587281845, 4587281834, 4587281844, 4587281836, 4587281843, 4587281846], "tags": {"access": "private", "leisure": "playground"}}, {"type": "way", "id": 468521223, "nodes": [5764146091, 5764146092, 7792241322, 5764146105, 2630495295, 4630533836, 2930965442, 2630495288, 2932363202, 2630495284, 2932363019, 2932362622, 2932362712, 2932362802, 2932363001, 2932362602, 2932362608, 2932362610, 4630533834, 5764146081, 2932363036, 5764146083, 5764146057, 12039816186, 5764146091], "tags": {"leisure": "park", "name": "Karower Damm", "name:etymology:wikipedia": "de:Berlin-Blankenburg", "protection_title": "Gesch\u00fctzte Gr\u00fcnanlage"}}, {"type": "way", "id": 608397664, "nodes": [5764073139, 5764073147, 5764073140, 5764073146, 5764073145, 5764073144, 5764073143, 4554145625, 4554145638, 4554145637, 4899844400, 4554145636, 4899844401, 4554145635, 4554145634, 4554145633, 5764073141, 5764073142, 1636871893, 5764073131, 5764073130, 5764073129, 5764073132, 5764073139], "tags": {"access": "private", "leisure": "park"}}, {"type": "way", "id": 1022837011, "nodes": [1828398435, 9433295346, 9433295375, 9433267906, 559696898, 9433295374, 4937114677, 9433295373, 9433295372, 9433295371, 9433295370, 9433295369, 9433295368, 9433295367, 9433295333, 9433295366, 9433295365, 9433295364, 9433295363, 9433295362, 9433295361, 9433295360, 9433295359, 9433295358, 9433295357, 9433295356, 9433295355, 9433295354, 9433295353, 9433295352, 9433295351, 9433295350, 9433295349, 9433295348, 9433295347, 1828398584, 9433295377, 1828398435], "tags": {"leisure": "park"}}]}